<BASICGAMECONFIGURATIONS>
    <MONEYTREE>
        <NUMBEROFQUESTIONS>15</NUMBEROFQUESTIONS>
        <DECIMALSEPARATOR></DECIMALSEPARATOR>
        <VARIABLESAFETYNET>NO</VARIABLESAFETYNET>
        <LIFELINEDEPENDANTSAFETYNET>10</LIFELINEDEPENDANTSAFETYNET>
        <LEVEL>
            <POSITION>15</POSITION>
            <REALVALUE>1000000</REALVALUE>
            <PREVIEWVALUE>$1 MILLION</PREVIEWVALUE>
			<SAFEHEAVEN>1</SAFEHEAVEN>
        </LEVEL>
        <LEVEL>
            <POSITION>14</POSITION>		
            <REALVALUE>500000</REALVALUE>
            <PREVIEWVALUE>$500.000</PREVIEWVALUE>
			<SAFEHEAVEN>0</SAFEHEAVEN>
        </LEVEL>
        <LEVEL>
            <POSITION>13</POSITION>		
            <REALVALUE>250000</REALVALUE>
            <PREVIEWVALUE>$250.000</PREVIEWVALUE>
			<SAFEHEAVEN>0</SAFEHEAVEN>			
        </LEVEL>		
        <LEVEL>
            <POSITION>12</POSITION>		
            <REALVALUE>125000</REALVALUE>
            <PREVIEWVALUE>$125.000</PREVIEWVALUE>
			<SAFEHEAVEN>0</SAFEHEAVEN>			
        </LEVEL>
        <LEVEL>
            <POSITION>11</POSITION>		
            <REALVALUE>64000</REALVALUE>
            <PREVIEWVALUE>$64.000</PREVIEWVALUE>
			<SAFEHEAVEN>0</SAFEHEAVEN>			
        </LEVEL>
        <LEVEL>
            <POSITION>10</POSITION>		
            <REALVALUE>32000</REALVALUE>
            <PREVIEWVALUE>$32.000</PREVIEWVALUE>
			<SAFEHEAVEN>0</SAFEHEAVEN>			
        </LEVEL>
        <LEVEL>
            <POSITION>9</POSITION>		
            <REALVALUE>16000</REALVALUE>
            <PREVIEWVALUE>$16.000</PREVIEWVALUE>
			<SAFEHEAVEN>0</SAFEHEAVEN>			
        </LEVEL>		
        <LEVEL>
            <POSITION>8</POSITION>		
            <REALVALUE>8000</REALVALUE>
            <PREVIEWVALUE>$8.000</PREVIEWVALUE>
			<SAFEHEAVEN>0</SAFEHEAVEN>			
        </LEVEL>		
        <LEVEL>
            <POSITION>7</POSITION>		
            <REALVALUE>4000</REALVALUE>
            <PREVIEWVALUE>$4.000</PREVIEWVALUE>
			<SAFEHEAVEN>0</SAFEHEAVEN>			
        </LEVEL>	
        <LEVEL>
            <POSITION>6</POSITION>		
            <REALVALUE>2000</REALVALUE>
            <PREVIEWVALUE>$2.000</PREVIEWVALUE>
			<SAFEHEAVEN>0</SAFEHEAVEN>			
        </LEVEL>		
        <LEVEL>
            <POSITION>5</POSITION>		
            <REALVALUE>1000</REALVALUE>
            <PREVIEWVALUE>$1.000</PREVIEWVALUE>
			<SAFEHEAVEN>1</SAFEHEAVEN>			
        </LEVEL>			
        <LEVEL>
            <POSITION>4</POSITION>		
            <REALVALUE>500</REALVALUE>
            <PREVIEWVALUE>$500</PREVIEWVALUE>
			<SAFEHEAVEN>0</SAFEHEAVEN>			
        </LEVEL>		
        <LEVEL>
            <POSITION>3</POSITION>		
            <REALVALUE>300</REALVALUE>
            <PREVIEWVALUE>$300</PREVIEWVALUE>
			<SAFEHEAVEN>0</SAFEHEAVEN>			
        </LEVEL>		
        <LEVEL>
            <POSITION>2</POSITION>		
            <REALVALUE>200</REALVALUE>
            <PREVIEWVALUE>$200</PREVIEWVALUE>
			<SAFEHEAVEN>0</SAFEHEAVEN>			
        </LEVEL>	
        <LEVEL>
            <POSITION>1</POSITION>		
            <REALVALUE>100</REALVALUE>
            <PREVIEWVALUE>$100</PREVIEWVALUE>
			<SAFEHEAVEN>0</SAFEHEAVEN>			
        </LEVEL>			
    </MONEYTREE>
    <LIFELINES>
        <DEFAULTLIFELINECOUNT>3</DEFAULTLIFELINECOUNT>
        <LIFELINE1>5050</LIFELINE1>
        <LIFELINE2>DDIP</LIFELINE2>
        <LIFELINE3>PAF</LIFELINE3>
        <LIFELINE4>STQ</LIFELINE4>
        <LIFELINE5>ATH</LIFELINE5>
    </LIFELINES>
</BASICGAMECONFIGURATIONS>